CHANGELOG.txt
LICENCE.txt
MANIFEST.in
README.md
README.txt
setup.py
raghavcalculator/__init__.py
raghavcalculator/cal.py
raghavcalculator.egg-info/PKG-INFO
raghavcalculator.egg-info/SOURCES.txt
raghavcalculator.egg-info/dependency_links.txt
raghavcalculator.egg-info/requires.txt
raghavcalculator.egg-info/top_level.txt